sophisticate/__init__.py
sophisticate-1.1.0.dist-info/LICENSE
sophisticate-1.1.0.dist-info/METADATA
sophisticate-1.1.0.dist-info/WHEEL
sophisticate-1.1.0.dist-info/top_level.txt
sophisticate-1.1.0.dist-info/RECORD
