Metadata-Version: 2.1
Name: sophisticate
Version: 1.1.0
Summary: Sophisticate Libraries Collection
Home-page: https://pypi.org/project/sophisticate/
Author: khiat Mohammed Abderrezzak
Author-email: khiat.dev@gmail.com
License: MIT
Classifier: Programming Language :: Python :: 3
Classifier: Operating System :: OS Independent
Classifier: License :: OSI Approved :: MIT License
License-File: LICENSE
Requires-Dist: conf-mat (>=1.1.0)
Requires-Dist: court-queue (>=1.0.4)
Requires-Dist: cqueue (>=1.1.2)
Requires-Dist: dictQ (>=1.0.0)
Requires-Dist: hashall (>=1.0.3)
Requires-Dist: hashtbl (>=1.0.5)
Requires-Dist: heep (>=1.0.2)
Requires-Dist: linkedit (>=1.1.3)
Requires-Dist: lstack (>=1.1.1)
Requires-Dist: ntwrk (>=1.0.2)
Requires-Dist: thri (>=1.0.5)
Requires-Dist: vsort (>=1.0.2)
